SQLThunder/__init__.py
SQLThunder/__main__.py
SQLThunder/__version__.py
SQLThunder/py.typed
SQLThunder/core/__init__.py
SQLThunder/core/client.py
SQLThunder/core/session.py
SQLThunder/exceptions/__init__.py
SQLThunder/exceptions/base.py
SQLThunder/exceptions/config.py
SQLThunder/exceptions/dbclient.py
SQLThunder/exceptions/execution.py
SQLThunder/exceptions/file_io.py
SQLThunder/exceptions/sql_conversion.py
SQLThunder/logging_config/__init__.py
SQLThunder/logging_config/logger.py
SQLThunder/utils/__init__.py
SQLThunder/utils/config.py
SQLThunder/utils/engine.py
SQLThunder/utils/file_io.py
SQLThunder/utils/insert_helpers.py
SQLThunder/utils/sql_conversion.py
sqlthunder-1.0.3.dist-info/licenses/LICENSE
sqlthunder-1.0.3.dist-info/METADATA
sqlthunder-1.0.3.dist-info/WHEEL
sqlthunder-1.0.3.dist-info/entry_points.txt
sqlthunder-1.0.3.dist-info/top_level.txt
sqlthunder-1.0.3.dist-info/RECORD
