Metadata-Version: 2.4
Name: SQLThunder
Version: 1.0.3
Summary: A flexible, high-level SQL client for Python that simplifies database interactions across SQLite, MySQL, and PostgreSQL
Home-page: https://github.com/ilovetartimiel/SQLThunder
Author: Hugo Garcia
Author-email: hugo.g.garcia@mail.mcgill.ca
License: MIT
Classifier: Development Status :: 5 - Production/Stable
Classifier: Intended Audience :: Developers
Classifier: Intended Audience :: Information Technology
Classifier: Intended Audience :: Science/Research
Classifier: Intended Audience :: Education
Classifier: Intended Audience :: End Users/Desktop
Classifier: License :: OSI Approved :: MIT License
Classifier: Programming Language :: Python :: 3
Classifier: Programming Language :: Python :: 3.8
Classifier: Programming Language :: Python :: 3.9
Classifier: Programming Language :: Python :: 3.10
Classifier: Programming Language :: Python :: 3.11
Classifier: Programming Language :: Python :: 3.12
Classifier: Topic :: Database
Classifier: Topic :: Scientific/Engineering :: Information Analysis
Classifier: Topic :: Software Development :: Libraries :: Python Modules
Classifier: Topic :: Utilities
Requires-Python: >=3.9
License-File: LICENSE
Requires-Dist: SQLAlchemy>=1.4
Requires-Dist: pandas>=1.4
Requires-Dist: PyYAML>=5.4
Requires-Dist: PyMySQL>=1.0
Requires-Dist: psycopg2-binary>=2.9
Requires-Dist: sqlparse>=0.4
Requires-Dist: cryptography>=38.0
Requires-Dist: openpyxl>=3.0
Requires-Dist: numpy>=1.22
Requires-Dist: tqdm>=4.60
Provides-Extra: dev
Requires-Dist: pytest>=8.0; extra == "dev"
Requires-Dist: pytest-cov<6.0,>=2.12; extra == "dev"
Requires-Dist: flake8>=7.0; extra == "dev"
Requires-Dist: mypy>=1.0; extra == "dev"
Requires-Dist: black<25.0,>=24.0; extra == "dev"
Requires-Dist: isort>=6.0; extra == "dev"
Requires-Dist: coverage>=7.0; extra == "dev"
Requires-Dist: pre-commit>=3.6; extra == "dev"
Requires-Dist: types-PyYAML; extra == "dev"
Dynamic: license-file
